{
  "version": 4,
  "tree_id": "DAMIMAS_A21B_0434",
  "tree_name": "DAMIMAS_A21B_0434",
  "split": "train",
  "metadata": {
    "date": "2026-05-09",
    "session_id": "20260509-DAMIMAS-434",
    "number": 434,
    "generated_at": "2026-05-09T13:55:31.161Z",
    "variety": "DAMIMAS"
  },
  "images": {
    "side_1": {
      "filename": "DAMIMAS_A21B_0434_1.jpg",
      "label_file": "DAMIMAS_A21B_0434_1.txt",
      "side_index": 0,
      "side_label": "Side 1",
      "width": 960,
      "height": 1280,
      "bbox_count": 7,
      "annotations": [
        {
          "box_index": 0,
          "class_id": 1,
          "class_name": "B2",
          "bbox_yolo": [
            0.4375,
            0.446875,
            0.06875,
            0.065625
          ],
          "bbox_pixel": [
            387,
            530,
            453,
            614
          ]
        },
        {
          "box_index": 1,
          "class_id": 1,
          "class_name": "B2",
          "bbox_yolo": [
            0.623437,
            0.453516,
            0.042708,
            0.061719
          ],
          "bbox_pixel": [
            578,
            541,
            619,
            620
          ]
        },
        {
          "box_index": 2,
          "class_id": 2,
          "class_name": "B3",
          "bbox_yolo": [
            0.603646,
            0.416406,
            0.069792,
            0.06875
          ],
          "bbox_pixel": [
            546,
            489,
            613,
            577
          ]
        },
        {
          "box_index": 3,
          "class_id": 2,
          "class_name": "B3",
          "bbox_yolo": [
            0.526563,
            0.427734,
            0.067708,
            0.063281
          ],
          "bbox_pixel": [
            473,
            507,
            538,
            588
          ]
        },
        {
          "box_index": 4,
          "class_id": 2,
          "class_name": "B3",
          "bbox_yolo": [
            0.472396,
            0.395313,
            0.051042,
            0.053125
          ],
          "bbox_pixel": [
            429,
            472,
            478,
            540
          ]
        },
        {
          "box_index": 5,
          "class_id": 2,
          "class_name": "B3",
          "bbox_yolo": [
            0.420312,
            0.400391,
            0.048958,
            0.030469
          ],
          "bbox_pixel": [
            380,
            493,
            427,
            532
          ]
        },
        {
          "box_index": 6,
          "class_id": 3,
          "class_name": "B4",
          "bbox_yolo": [
            0.543229,
            0.378516,
            0.053125,
            0.038281
          ],
          "bbox_pixel": [
            496,
            460,
            547,
            509
          ]
        }
      ]
    },
    "side_2": {
      "filename": "DAMIMAS_A21B_0434_2.jpg",
      "label_file": "DAMIMAS_A21B_0434_2.txt",
      "side_index": 1,
      "side_label": "Side 2",
      "width": 960,
      "height": 1280,
      "bbox_count": 8,
      "annotations": [
        {
          "box_index": 0,
          "class_id": 1,
          "class_name": "B2",
          "bbox_yolo": [
            0.607292,
            0.563672,
            0.095833,
            0.064844
          ],
          "bbox_pixel": [
            537,
            680,
            629,
            763
          ]
        },
        {
          "box_index": 1,
          "class_id": 2,
          "class_name": "B3",
          "bbox_yolo": [
            0.533854,
            0.541797,
            0.069792,
            0.064844
          ],
          "bbox_pixel": [
            479,
            652,
            546,
            735
          ]
        },
        {
          "box_index": 2,
          "class_id": 2,
          "class_name": "B3",
          "bbox_yolo": [
            0.444271,
            0.558984,
            0.071875,
            0.060156
          ],
          "bbox_pixel": [
            392,
            677,
            461,
            754
          ]
        },
        {
          "box_index": 3,
          "class_id": 2,
          "class_name": "B3",
          "bbox_yolo": [
            0.467187,
            0.503516,
            0.044792,
            0.053906
          ],
          "bbox_pixel": [
            427,
            610,
            470,
            679
          ]
        },
        {
          "box_index": 4,
          "class_id": 2,
          "class_name": "B3",
          "bbox_yolo": [
            0.620833,
            0.50625,
            0.06875,
            0.05625
          ],
          "bbox_pixel": [
            563,
            612,
            629,
            684
          ]
        },
        {
          "box_index": 5,
          "class_id": 3,
          "class_name": "B4",
          "bbox_yolo": [
            0.541667,
            0.480469,
            0.06875,
            0.046875
          ],
          "bbox_pixel": [
            487,
            585,
            553,
            645
          ]
        },
        {
          "box_index": 6,
          "class_id": 3,
          "class_name": "B4",
          "bbox_yolo": [
            0.447396,
            0.455078,
            0.036458,
            0.050781
          ],
          "bbox_pixel": [
            412,
            550,
            447,
            615
          ]
        },
        {
          "box_index": 7,
          "class_id": 2,
          "class_name": "B3",
          "bbox_yolo": [
            0.414063,
            0.516016,
            0.034375,
            0.030469
          ],
          "bbox_pixel": [
            381,
            641,
            414,
            680
          ]
        }
      ]
    },
    "side_3": {
      "filename": "DAMIMAS_A21B_0434_3.jpg",
      "label_file": "DAMIMAS_A21B_0434_3.txt",
      "side_index": 2,
      "side_label": "Side 3",
      "width": 960,
      "height": 1280,
      "bbox_count": 6,
      "annotations": [
        {
          "box_index": 0,
          "class_id": 2,
          "class_name": "B3",
          "bbox_yolo": [
            0.528646,
            0.515625,
            0.103125,
            0.084375
          ],
          "bbox_pixel": [
            458,
            606,
            557,
            714
          ]
        },
        {
          "box_index": 1,
          "class_id": 2,
          "class_name": "B3",
          "bbox_yolo": [
            0.526563,
            0.458203,
            0.076042,
            0.047656
          ],
          "bbox_pixel": [
            469,
            556,
            542,
            617
          ]
        },
        {
          "box_index": 2,
          "class_id": 1,
          "class_name": "B2",
          "bbox_yolo": [
            0.320313,
            0.516016,
            0.059375,
            0.049219
          ],
          "bbox_pixel": [
            279,
            629,
            336,
            692
          ]
        },
        {
          "box_index": 3,
          "class_id": 2,
          "class_name": "B3",
          "bbox_yolo": [
            0.4375,
            0.479687,
            0.060417,
            0.06875
          ],
          "bbox_pixel": [
            391,
            570,
            449,
            658
          ]
        },
        {
          "box_index": 4,
          "class_id": 2,
          "class_name": "B3",
          "bbox_yolo": [
            0.359375,
            0.491797,
            0.047917,
            0.047656
          ],
          "bbox_pixel": [
            322,
            599,
            368,
            660
          ]
        },
        {
          "box_index": 5,
          "class_id": 2,
          "class_name": "B3",
          "bbox_yolo": [
            0.329688,
            0.454688,
            0.059375,
            0.040625
          ],
          "bbox_pixel": [
            288,
            556,
            345,
            608
          ]
        }
      ]
    },
    "side_4": {
      "filename": "DAMIMAS_A21B_0434_4.jpg",
      "label_file": "DAMIMAS_A21B_0434_4.txt",
      "side_index": 3,
      "side_label": "Side 4",
      "width": 960,
      "height": 1280,
      "bbox_count": 3,
      "annotations": [
        {
          "box_index": 0,
          "class_id": 2,
          "class_name": "B3",
          "bbox_yolo": [
            0.616146,
            0.45625,
            0.113542,
            0.085938
          ],
          "bbox_pixel": [
            537,
            529,
            646,
            639
          ]
        },
        {
          "box_index": 1,
          "class_id": 1,
          "class_name": "B2",
          "bbox_yolo": [
            0.486979,
            0.460547,
            0.090625,
            0.078906
          ],
          "bbox_pixel": [
            424,
            539,
            511,
            640
          ]
        },
        {
          "box_index": 2,
          "class_id": 2,
          "class_name": "B3",
          "bbox_yolo": [
            0.435937,
            0.411328,
            0.051042,
            0.057031
          ],
          "bbox_pixel": [
            394,
            490,
            443,
            563
          ]
        }
      ]
    }
  },
  "bunches": [
    {
      "bunch_id": 1,
      "class": "B2",
      "class_mismatch": false,
      "appearance_count": 2,
      "appearances": [
        {
          "side": "side_1",
          "side_index": 0,
          "box_index": 0,
          "class_name": "B2",
          "bbox_pixel": [
            387,
            530,
            453,
            614
          ]
        },
        {
          "side": "side_2",
          "side_index": 1,
          "box_index": 0,
          "class_name": "B2",
          "bbox_pixel": [
            537,
            680,
            629,
            763
          ]
        }
      ]
    },
    {
      "bunch_id": 2,
      "class": "B2",
      "class_mismatch": false,
      "appearance_count": 3,
      "appearances": [
        {
          "side": "side_1",
          "side_index": 0,
          "box_index": 1,
          "class_name": "B2",
          "bbox_pixel": [
            578,
            541,
            619,
            620
          ]
        },
        {
          "side": "side_3",
          "side_index": 2,
          "box_index": 2,
          "class_name": "B2",
          "bbox_pixel": [
            279,
            629,
            336,
            692
          ]
        },
        {
          "side": "side_4",
          "side_index": 3,
          "box_index": 1,
          "class_name": "B2",
          "bbox_pixel": [
            424,
            539,
            511,
            640
          ]
        }
      ]
    },
    {
      "bunch_id": 3,
      "class": "B3",
      "class_mismatch": false,
      "appearance_count": 3,
      "appearances": [
        {
          "side": "side_1",
          "side_index": 0,
          "box_index": 2,
          "class_name": "B3",
          "bbox_pixel": [
            546,
            489,
            613,
            577
          ]
        },
        {
          "side": "side_3",
          "side_index": 2,
          "box_index": 5,
          "class_name": "B3",
          "bbox_pixel": [
            288,
            556,
            345,
            608
          ]
        },
        {
          "side": "side_4",
          "side_index": 3,
          "box_index": 2,
          "class_name": "B3",
          "bbox_pixel": [
            394,
            490,
            443,
            563
          ]
        }
      ]
    },
    {
      "bunch_id": 4,
      "class": "B3",
      "class_mismatch": false,
      "appearance_count": 1,
      "appearances": [
        {
          "side": "side_1",
          "side_index": 0,
          "box_index": 3,
          "class_name": "B3",
          "bbox_pixel": [
            473,
            507,
            538,
            588
          ]
        }
      ]
    },
    {
      "bunch_id": 5,
      "class": "B3",
      "class_mismatch": false,
      "appearance_count": 1,
      "appearances": [
        {
          "side": "side_1",
          "side_index": 0,
          "box_index": 4,
          "class_name": "B3",
          "bbox_pixel": [
            429,
            472,
            478,
            540
          ]
        }
      ]
    },
    {
      "bunch_id": 6,
      "class": "B3",
      "class_mismatch": false,
      "appearance_count": 2,
      "appearances": [
        {
          "side": "side_1",
          "side_index": 0,
          "box_index": 5,
          "class_name": "B3",
          "bbox_pixel": [
            380,
            493,
            427,
            532
          ]
        },
        {
          "side": "side_2",
          "side_index": 1,
          "box_index": 4,
          "class_name": "B3",
          "bbox_pixel": [
            563,
            612,
            629,
            684
          ]
        }
      ]
    },
    {
      "bunch_id": 7,
      "class": "B4",
      "class_mismatch": false,
      "appearance_count": 1,
      "appearances": [
        {
          "side": "side_1",
          "side_index": 0,
          "box_index": 6,
          "class_name": "B4",
          "bbox_pixel": [
            496,
            460,
            547,
            509
          ]
        }
      ]
    },
    {
      "bunch_id": 8,
      "class": "B3",
      "class_mismatch": false,
      "appearance_count": 1,
      "appearances": [
        {
          "side": "side_2",
          "side_index": 1,
          "box_index": 1,
          "class_name": "B3",
          "bbox_pixel": [
            479,
            652,
            546,
            735
          ]
        }
      ]
    },
    {
      "bunch_id": 9,
      "class": "B3",
      "class_mismatch": false,
      "appearance_count": 2,
      "appearances": [
        {
          "side": "side_2",
          "side_index": 1,
          "box_index": 2,
          "class_name": "B3",
          "bbox_pixel": [
            392,
            677,
            461,
            754
          ]
        },
        {
          "side": "side_3",
          "side_index": 2,
          "box_index": 0,
          "class_name": "B3",
          "bbox_pixel": [
            458,
            606,
            557,
            714
          ]
        }
      ]
    },
    {
      "bunch_id": 10,
      "class": "B3",
      "class_mismatch": false,
      "appearance_count": 2,
      "appearances": [
        {
          "side": "side_2",
          "side_index": 1,
          "box_index": 3,
          "class_name": "B3",
          "bbox_pixel": [
            427,
            610,
            470,
            679
          ]
        },
        {
          "side": "side_3",
          "side_index": 2,
          "box_index": 1,
          "class_name": "B3",
          "bbox_pixel": [
            469,
            556,
            542,
            617
          ]
        }
      ]
    },
    {
      "bunch_id": 11,
      "class": "B4",
      "class_mismatch": false,
      "appearance_count": 1,
      "appearances": [
        {
          "side": "side_2",
          "side_index": 1,
          "box_index": 5,
          "class_name": "B4",
          "bbox_pixel": [
            487,
            585,
            553,
            645
          ]
        }
      ]
    },
    {
      "bunch_id": 12,
      "class": "B4",
      "class_mismatch": false,
      "appearance_count": 1,
      "appearances": [
        {
          "side": "side_2",
          "side_index": 1,
          "box_index": 6,
          "class_name": "B4",
          "bbox_pixel": [
            412,
            550,
            447,
            615
          ]
        }
      ]
    },
    {
      "bunch_id": 13,
      "class": "B3",
      "class_mismatch": false,
      "appearance_count": 2,
      "appearances": [
        {
          "side": "side_2",
          "side_index": 1,
          "box_index": 7,
          "class_name": "B3",
          "bbox_pixel": [
            381,
            641,
            414,
            680
          ]
        },
        {
          "side": "side_3",
          "side_index": 2,
          "box_index": 3,
          "class_name": "B3",
          "bbox_pixel": [
            391,
            570,
            449,
            658
          ]
        }
      ]
    },
    {
      "bunch_id": 14,
      "class": "B3",
      "class_mismatch": false,
      "appearance_count": 2,
      "appearances": [
        {
          "side": "side_3",
          "side_index": 2,
          "box_index": 4,
          "class_name": "B3",
          "bbox_pixel": [
            322,
            599,
            368,
            660
          ]
        },
        {
          "side": "side_4",
          "side_index": 3,
          "box_index": 0,
          "class_name": "B3",
          "bbox_pixel": [
            537,
            529,
            646,
            639
          ]
        }
      ]
    }
  ],
  "_confirmedLinks": [
    {
      "linkId": "lnk-0",
      "sideA": 0,
      "bboxIdA": "b0",
      "sideB": 1,
      "bboxIdB": "b0"
    },
    {
      "linkId": "lnk-1",
      "sideA": 0,
      "bboxIdA": "b5",
      "sideB": 1,
      "bboxIdB": "b4"
    },
    {
      "linkId": "lnk-2",
      "sideA": 1,
      "bboxIdA": "b2",
      "sideB": 2,
      "bboxIdB": "b0"
    },
    {
      "linkId": "lnk-3",
      "sideA": 1,
      "bboxIdA": "b3",
      "sideB": 2,
      "bboxIdB": "b1"
    },
    {
      "linkId": "lnk-4",
      "sideA": 1,
      "bboxIdA": "b7",
      "sideB": 2,
      "bboxIdB": "b3"
    },
    {
      "linkId": "lnk-5",
      "sideA": 2,
      "bboxIdA": "b2",
      "sideB": 3,
      "bboxIdB": "b1"
    },
    {
      "linkId": "lnk-6",
      "sideA": 3,
      "bboxIdA": "b1",
      "sideB": 0,
      "bboxIdB": "b1"
    },
    {
      "linkId": "lnk-7",
      "sideA": 2,
      "bboxIdA": "b4",
      "sideB": 3,
      "bboxIdB": "b0"
    },
    {
      "linkId": "lnk-8",
      "sideA": 2,
      "bboxIdA": "b5",
      "sideB": 3,
      "bboxIdB": "b2"
    },
    {
      "linkId": "lnk-9",
      "sideA": 3,
      "bboxIdA": "b2",
      "sideB": 0,
      "bboxIdB": "b2"
    }
  ],
  "summary": {
    "total_unique_bunches": 14,
    "total_detections": 24,
    "duplicates_linked": 10,
    "by_class": {
      "B1": 0,
      "B2": 2,
      "B3": 9,
      "B4": 3,
      "other": 0
    },
    "by_side": {
      "side_1": 7,
      "side_2": 8,
      "side_3": 6,
      "side_4": 3
    }
  }
}
