{"tree_name": "LONSUM_A21A_0052", "split": "train", "source": "y26s_nopretrained_inference", "weights": "baseline-run/weights/y26s_nopretrained.pt", "images": {"sisi_1": {"annotations": [{"box_index": 0, "class_id": 2, "class_name": "B3", "bbox_yolo": [0.677166759967804, 0.5585098266601562, 0.06664779037237167, 0.07486515492200851], "conf": 0.26980990171432495}]}, "sisi_2": {"annotations": []}, "sisi_3": {"annotations": []}, "sisi_4": {"annotations": [{"box_index": 0, "class_id": 2, "class_name": "B3", "bbox_yolo": [0.6276516318321228, 0.41452500224113464, 0.06983128190040588, 0.07291422039270401], "conf": 0.3028852939605713}, {"box_index": 1, "class_id": 2, "class_name": "B3", "bbox_yolo": [0.5603123903274536, 0.3677079677581787, 0.06939738988876343, 0.0723339095711708], "conf": 0.25048768520355225}]}}}