{"tree_name": "LONSUM_A21A_0016", "split": "unknown", "detector": "y26m", "images": {"side_1": {"side_index": 0, "annotations": []}, "side_2": {"side_index": 1, "annotations": [{"class_name": "B3", "bbox_yolo": [0.4377441108226776, 0.44295939803123474, 0.1368822455406189, 0.11353950947523117], "conf": 0.5704570412635803}]}, "side_3": {"side_index": 2, "annotations": [{"class_name": "B4", "bbox_yolo": [0.3968313932418823, 0.4460526406764984, 0.07675205916166306, 0.07149696350097656], "conf": 0.28910133242607117}]}, "side_4": {"side_index": 3, "annotations": []}}}